setup_flask_app/__init__.py
setup_flask_app/cli.py
setup_flask_app/funcs.py
tests/__init__.py
tests/test_cli.py
setup_flask_app-0.0.2.dist-info/LICENSE
setup_flask_app-0.0.2.dist-info/METADATA
setup_flask_app-0.0.2.dist-info/WHEEL
setup_flask_app-0.0.2.dist-info/entry_points.txt
setup_flask_app-0.0.2.dist-info/top_level.txt
setup_flask_app-0.0.2.dist-info/RECORD
