Metadata-Version: 2.1
Name: setup-flask-app
Version: 0.0.2
Summary: A CLI to setup a flask app with just one command
Author: Saqib Tanveer
Author-email: <elven5055@gmail.com>
Keywords: python,flask,setup-flask-app,auto setup
Classifier: Development Status :: 1 - Planning
Classifier: Intended Audience :: Developers
Classifier: Programming Language :: Python :: 3
Classifier: Operating System :: Unix
Classifier: Operating System :: MacOS :: MacOS X
Classifier: Operating System :: Microsoft :: Windows
License-File: LICENSE
